taptaptap
