Metadata-Version: 1.1
Name: taptaptap
Version: 1.1.3
Summary: Test Anything Protocol handling for cats
Home-page: http://lukas-prokop.at/proj/taptaptap/
Author: Lukas Prokop
Author-email: admin@lukas-prokop.at
License: BSD
Platform: any
Classifier: Development Status :: 4 - Beta
Classifier: Environment :: Console
Classifier: Intended Audience :: Developers
Classifier: Intended Audience :: Information Technology
Classifier: License :: OSI Approved :: BSD License
Classifier: Natural Language :: English
Classifier: Operating System :: OS Independent
Classifier: Programming Language :: Python :: 2.7
Classifier: Topic :: Software Development :: Documentation
Classifier: Topic :: Software Development :: Build Tools
Classifier: Topic :: Software Development :: Testing
Classifier: Topic :: System :: Logging
Classifier: Topic :: System :: Systems Administration
